{
  "projects": [
    {
      "title": "klawka.pl",
      "desc": "Item shop for Minecraft server. Both frontend and backend were made by me.",
      "url": "https://klawka.pl/home",
      "imageFileName": "klawka.svg",
      "techIcons": ["2_Spring.svg", "5_React.svg", "6_JavaScript.svg", "3_MySql.svg"],
      "deployed": true
    },
    {
      "title": "BitMage",
      "desc": "Console app for generating ASCII images from files.",
      "url": "https://github.com/4thlas/BitMage",
      "imageFileName": "bitmage.svg",
      "techIcons": ["1_Java.svg"],
      "deployed": false
    },
    {
      "title": "VoTail - Frontend",
      "desc": "School project, simple voting system made with friends.",
      "url": "https://github.com/Votail/votail-frontend",
      "imageFileName": "VoTail.svg",
      "techIcons": ["5_React.svg", "6_JavaScript.svg"],
      "deployed": false
    }
  ]
}